{
  "acaiId": "person:Abishai",
  "name": "Abishai",
  "description": "A nephew of King David, and a leader of David’s mighty men.",
  "gender": "male",
  "father": "person:HusbandOfZeruiah",
  "mother": "person:Zeruiah",
  "tribe": "group:Judah",
  "roles": [
    "Military Commander",
    "Royal Family Member",
    "Warrior"
  ],
  "references": [
    "09026006",
    "09026007",
    "09026008",
    "09026009",
    "10002018",
    "10002024",
    "10003030",
    "10010010",
    "10010014",
    "10016009",
    "10016011",
    "10018002",
    "10018005",
    "10018012",
    "10019022",
    "10020006",
    "10020010",
    "10021017",
    "10023018",
    "13002016",
    "13011020",
    "13018012",
    "13019011",
    "13019015"
  ]
}
