{
  "acaiId": "person:Benjamin",
  "name": "Benjamin",
  "description": "The youngest son of the patriarch Jacob, and the second son of the matriarch Rachel. He was the founder of the tribe of Benjamin.",
  "gender": "male",
  "father": "person:Israel",
  "mother": "person:Rachel",
  "offspring": [
    "person:Bela",
    "person:Becher",
    "person:Ashbel",
    "person:Gera",
    "person:Naaman",
    "person:Ehi",
    "person:Rosh",
    "person:Muppim",
    "person:Huppim",
    "person:Ard",
    "person:Ahiram",
    "person:Jediael"
  ],
  "tribe": "group:Benjamin",
  "roles": [
    "Patriarch"
  ],
  "references": [
    "10002009",
    "10002015",
    "10002025",
    "10002031",
    "10003019",
    "10004002",
    "10016011",
    "10019017",
    "10019018",
    "10020001",
    "10021014",
    "10023029"
  ]
}
